mcap_to_mp4/__init__.py
mcap_to_mp4/_version.py
mcap_to_mp4/cli.py
mcap_to_mp4-0.3.0.dist-info/LICENSE
mcap_to_mp4-0.3.0.dist-info/METADATA
mcap_to_mp4-0.3.0.dist-info/WHEEL
mcap_to_mp4-0.3.0.dist-info/entry_points.txt
mcap_to_mp4-0.3.0.dist-info/RECORD
