Metadata-Version: 2.3
Name: mcap-to-mp4
Version: 0.3.0
Summary: A tool to convert ROS topics recored with mcap to MP4 file
License: MIT
Author: Daisuke Sato
Requires-Python: >=3.10,<4.0
Classifier: License :: OSI Approved :: MIT License
Classifier: Programming Language :: Python :: 3
Classifier: Programming Language :: Python :: 3.10
Classifier: Programming Language :: Python :: 3.11
Classifier: Programming Language :: Python :: 3.12
Classifier: Programming Language :: Python :: 3.13
Requires-Dist: imageio[ffmpeg] (>=2.34.0,<3.0.0)
Requires-Dist: mcap (>=1.1.1,<2.0.0)
Requires-Dist: mcap-ros2-support (>=0.5.3,<0.6.0)
Requires-Dist: numpy (>=1.26.4,<3.0.0)
Requires-Dist: pillow (>=10.2,<12.0)
Requires-Dist: poetry (>=1.8,<3.0)
Project-URL: Repository, https://github.com/Tiryoh/mcap-to-mp4
